mdopt/__init__.py
mdopt/backend/array.py
mdopt/contractor/__init__.py
mdopt/contractor/contractor.py
mdopt/mps/__init__.py
mdopt/mps/canonical.py
mdopt/mps/explicit.py
mdopt/mps/utils.py
mdopt/optimiser/__init__.py
mdopt/optimiser/dephasing_dmrg.py
mdopt/optimiser/dmrg.py
mdopt/optimiser/utils.py
mdopt/py.typed
mdopt/utils/__init__.py
mdopt/utils/utils.py
mdopt-1.1.1.dist-info/METADATA
mdopt-1.1.1.dist-info/WHEEL
mdopt-1.1.1.dist-info/licenses/LICENSE.md
mdopt-1.1.1.dist-info/RECORD
