Metadata-Version: 2.4
Name: mdopt
Version: 1.1.1
Summary: Discrete optimisation in the tensor-network (specifically, MPS-MPO) language.
License-Expression: MIT
License-File: LICENSE.md
Keywords: tensor networks,quantum error correction,discrete optimisation,MPS,MPO,python,decoding
Author: Aleksandr Berezutskii
Author-email: berezutskii.aleksandr@gmail.com
Maintainer: Aleksandr Berezutskii
Maintainer-email: berezutskii.aleksandr@gmail.com
Requires-Python: >=3.10,<4.0
Classifier: Programming Language :: Python
Classifier: Programming Language :: Python :: 3 :: Only
Classifier: Programming Language :: Python :: 3.10
Classifier: Programming Language :: Python :: 3.11
Classifier: Programming Language :: Python :: 3.12
Classifier: Programming Language :: Python :: 3.13
Classifier: Typing :: Typed
Requires-Dist: ldpc (>=2.3.6,<3.0.0)
Requires-Dist: matrex (>=0.0.1,<0.0.2)
Requires-Dist: more-itertools (>=8.12,<11.0)
Requires-Dist: numpy (<2.2.0)
Requires-Dist: opt-einsum (>=3.3.0,<4.0.0)
Requires-Dist: qecsim (>=1.0b9,<2.0.0)
Requires-Dist: qecstruct (>=0.2.9,<0.3.0)
Requires-Dist: qldpc (>=0.1.2,<0.2.0)
Requires-Dist: scipy (>=1.9.2,<2.0.0)
Requires-Dist: seaborn (>=0.13.2,<0.14.0)
Requires-Dist: sympy (>=1.14.0,<2.0.0)
Requires-Dist: threadpoolctl (>=3.1.0,<4.0.0)
Requires-Dist: tqdm (>=4.64.1,<5.0.0)
